sachin/__init__.py
sachin/perceptron.py
sachin_pkg_Sachinsen1295-0.0.3.dist-info/LICENSE
sachin_pkg_Sachinsen1295-0.0.3.dist-info/METADATA
sachin_pkg_Sachinsen1295-0.0.3.dist-info/WHEEL
sachin_pkg_Sachinsen1295-0.0.3.dist-info/top_level.txt
sachin_pkg_Sachinsen1295-0.0.3.dist-info/RECORD
