Metadata-Version: 2.1
Name: sachin-pkg-Sachinsen1295
Version: 0.0.3
Summary: A small package for perceptron
Home-page: https://github.com/Sachinsen1295/sachin-pkg
Author: Sachinsen1295
Author-email: sachin.sen1295@gmail.com
Project-URL: Bug Tracker, https://github.com/Sachinsen1295/sachin-pkg/issues
Classifier: Programming Language :: Python :: 3
Classifier: License :: OSI Approved :: MIT License
Classifier: Operating System :: OS Independent
Requires-Python: >=3.6
License-File: LICENSE
Requires-Dist: numpy (==1.21.6)
Requires-Dist: pandas (==1.1.5)
Requires-Dist: joblib (==1.2.0)
